enum/__init__.py
enum/general.py
logger/__init__.py
logger/colorfy.py
logger/logger.py
types/__init__.py
types/constant.py
funutils-0.0.1.dist-info/LICENSE.txt
funutils-0.0.1.dist-info/METADATA
funutils-0.0.1.dist-info/WHEEL
funutils-0.0.1.dist-info/top_level.txt
funutils-0.0.1.dist-info/RECORD
