Metadata-Version: 2.1
Name: funutils
Version: 0.0.1
Summary: Utility classes
Home-page: https://gitee.com/openwld/utilities
Author: Zheng ZhiWei
Author-email: jettzheng@foxmail.com
License: UNKNOWN
Platform: UNKNOWN
Classifier: Programming Language :: Python :: 3
Classifier: License :: OSI Approved :: MIT License
Classifier: Operating System :: OS Independent
Requires-Python: >=3.6
License-File: LICENSE.txt
